amapy/__init__.py
amapy/app.py
amapy/app_debug.py
amapy/arg_parse.py
amapy/plugins.py
amapy/commands/__init__.py
amapy/commands/base_action.py
amapy/commands/cli_action.py
amapy/commands/cli_option.py
amapy/commands/cmd_group.py
amapy/commands/parser.py
amapy/commands/alias_actions/__init__.py
amapy/commands/alias_actions/alias_add.py
amapy/commands/alias_actions/alias_help.py
amapy/commands/alias_actions/alias_info.py
amapy/commands/alias_actions/alias_remove.py
amapy/commands/alias_actions/alias_set.py
amapy/commands/asset_actions/__init__.py
amapy/commands/asset_actions/add.py
amapy/commands/asset_actions/clone.py
amapy/commands/asset_actions/commit.py
amapy/commands/asset_actions/cp.py
amapy/commands/asset_actions/dashboard.py
amapy/commands/asset_actions/debug.py
amapy/commands/asset_actions/delete.py
amapy/commands/asset_actions/diff.py
amapy/commands/asset_actions/discard.py
amapy/commands/asset_actions/download.py
amapy/commands/asset_actions/fetch.py
amapy/commands/asset_actions/find.py
amapy/commands/asset_actions/hash.py
amapy/commands/asset_actions/history.py
amapy/commands/asset_actions/info.py
amapy/commands/asset_actions/init.py
amapy/commands/asset_actions/list.py
amapy/commands/asset_actions/pull.py
amapy/commands/asset_actions/remote.py
amapy/commands/asset_actions/remove.py
amapy/commands/asset_actions/report.py
amapy/commands/asset_actions/restore.py
amapy/commands/asset_actions/status.py
amapy/commands/asset_actions/switch.py
amapy/commands/asset_actions/tree.py
amapy/commands/asset_actions/union.py
amapy/commands/asset_actions/update.py
amapy/commands/asset_actions/upload.py
amapy/commands/asset_actions/user_prompt_setting.py
amapy/commands/asset_actions/versions.py
amapy/commands/asset_actions/tests/__init__.py
amapy/commands/asset_actions/tests/test_add.py
amapy/commands/asset_actions/tests/test_asset_cmds.py
amapy/commands/asset_actions/tests/test_info.py
amapy/commands/asset_class_actions/__init__.py
amapy-1.0.1.dist-info/METADATA
amapy-1.0.1.dist-info/WHEEL
amapy-1.0.1.dist-info/entry_points.txt
amapy-1.0.1.dist-info/top_level.txt
amapy-1.0.1.dist-info/RECORD
