Metadata-Version: 2.1
Name: amapy
Version: 1.0.1
Summary: The client side tool for ama project.
Author-email: Swarup Mahanti <swarup.mahanti@roche.com>
Maintainer-email: Swarup Mahanti <swarup.mahanti@roche.com>
License: Copyright (c) 2024 Roche Diagnostics Computation Science & Informatics
Requires-Python: <3.11,>=3.10
Requires-Dist: amapy-contents==1.0.1
Requires-Dist: amapy-core==1.0.1
Requires-Dist: amapy-db==1.0.1
Requires-Dist: amapy-pluggy==1.0.1
Requires-Dist: amapy-plugin-gcr==1.0.1
Requires-Dist: amapy-plugin-gcs==1.0.1
Requires-Dist: amapy-plugin-posix==1.0.1
Requires-Dist: amapy-plugin-s3==1.0.1
Requires-Dist: amapy-utils==1.0.1
Requires-Dist: markupsafe==2.1.*
